triton_shm_client/__init__.py
triton_shm_client/client.py
triton_shm_client/pool.py
triton_shm_client-0.1.0.dist-info/licenses/LICENSE
triton_shm_client-0.1.0.dist-info/METADATA
triton_shm_client-0.1.0.dist-info/WHEEL
triton_shm_client-0.1.0.dist-info/top_level.txt
triton_shm_client-0.1.0.dist-info/RECORD
