Metadata-Version: 2.4
Name: triton-shm-client
Version: 0.1.0
Summary: Easier Shared Memory management for Triton Inference Client
Author: Armaggheddon
License: MIT
Requires-Python: >=3.10
License-File: LICENSE
Requires-Dist: tritonclient[all]>=2.63.0
Requires-Dist: numpy>=2.2.6
Provides-Extra: dev
Requires-Dist: pytest; extra == "dev"
Requires-Dist: black; extra == "dev"
Requires-Dist: flake8; extra == "dev"
Dynamic: license-file
